voicerun_completions/__init__.py
voicerun_completions/client.py
voicerun_completions/retry.py
voicerun_completions/providers/base.py
voicerun_completions/providers/anthropic/anthropic_client.py
voicerun_completions/providers/anthropic/streaming.py
voicerun_completions/providers/anthropic/utils.py
voicerun_completions/providers/google/google_client.py
voicerun_completions/providers/google/streaming.py
voicerun_completions/providers/google/utils.py
voicerun_completions/providers/openai/openai_client.py
voicerun_completions/providers/openai/streaming.py
voicerun_completions/providers/openai/utils.py
voicerun_completions/providers/vertex_anthropic/__init__.py
voicerun_completions/providers/vertex_anthropic/vertex_anthropic_client.py
voicerun_completions/types/cache.py
voicerun_completions/types/messages.py
voicerun_completions/types/request.py
voicerun_completions/types/response.py
voicerun_completions/types/streaming.py
voicerun_completions/utils/streaming.py
voicerun_completions-0.2.0.dist-info/METADATA
voicerun_completions-0.2.0.dist-info/WHEEL
voicerun_completions-0.2.0.dist-info/top_level.txt
voicerun_completions-0.2.0.dist-info/RECORD
