Metadata-Version: 2.4
Name: voicerun_completions
Version: 0.2.0
Summary: VoiceRun Completions
Author: VoiceRun
Requires-Python: >=3.10
Requires-Dist: loguru
Requires-Dist: black>=23.3.0
Requires-Dist: openai==2.8.0
Requires-Dist: anthropic==0.74.0
Requires-Dist: google-genai==1.56.0
